optimizingdataanalysisprograms/__init__.py
optimizingdataanalysisprograms/odp.py
optimizingdataanalysisprograms-1.0.1.dist-info/METADATA
optimizingdataanalysisprograms-1.0.1.dist-info/WHEEL
optimizingdataanalysisprograms-1.0.1.dist-info/top_level.txt
optimizingdataanalysisprograms-1.0.1.dist-info/RECORD
